odoo/addons/ssi_fixed_asset_from_inventory/README.rst
odoo/addons/ssi_fixed_asset_from_inventory/__init__.py
odoo/addons/ssi_fixed_asset_from_inventory/__manifest__.py
odoo/addons/ssi_fixed_asset_from_inventory/data/account_journal_data.xml
odoo/addons/ssi_fixed_asset_from_inventory/data/approval_template_data.xml
odoo/addons/ssi_fixed_asset_from_inventory/data/ir_sequence_data.xml
odoo/addons/ssi_fixed_asset_from_inventory/data/policy_template_data.xml
odoo/addons/ssi_fixed_asset_from_inventory/data/sequence_template_data.xml
odoo/addons/ssi_fixed_asset_from_inventory/i18n/id.po
odoo/addons/ssi_fixed_asset_from_inventory/i18n/ssi_fixed_asset_from_inventory.pot
odoo/addons/ssi_fixed_asset_from_inventory/models/__init__.py
odoo/addons/ssi_fixed_asset_from_inventory/models/fixed_asset_from_inventory.py
odoo/addons/ssi_fixed_asset_from_inventory/models/fixed_asset_from_inventory_type.py
odoo/addons/ssi_fixed_asset_from_inventory/security/ir.model.access.csv
odoo/addons/ssi_fixed_asset_from_inventory/security/ir_module_category_data.xml
odoo/addons/ssi_fixed_asset_from_inventory/security/ir_rule_data.xml
odoo/addons/ssi_fixed_asset_from_inventory/security/res_group_data.xml
odoo/addons/ssi_fixed_asset_from_inventory/static/description/banner.png
odoo/addons/ssi_fixed_asset_from_inventory/static/description/icon.png
odoo/addons/ssi_fixed_asset_from_inventory/views/fixed_asset_from_inventory_type_views.xml
odoo/addons/ssi_fixed_asset_from_inventory/views/fixed_asset_from_inventory_views.xml
odoo14_addon_ssi_fixed_asset_from_inventory-14.0.1.1.0.dist-info/METADATA
odoo14_addon_ssi_fixed_asset_from_inventory-14.0.1.1.0.dist-info/WHEEL
odoo14_addon_ssi_fixed_asset_from_inventory-14.0.1.1.0.dist-info/top_level.txt
odoo14_addon_ssi_fixed_asset_from_inventory-14.0.1.1.0.dist-info/RECORD
