Metadata-Version: 2.1
Name: odoo14-addon-ssi_fixed_asset_from_inventory
Version: 14.0.1.1.0
Summary: Fixed Asset From Inventory
Home-page: https://simetri-sinergi.id
Author: PT. Simetri Sinergi Indonesia, OpenSynergy Indonesia
License: AGPL-3
Classifier: Programming Language :: Python
Classifier: Framework :: Odoo
Classifier: Framework :: Odoo :: 14.0
Classifier: License :: OSI Approved :: GNU Affero General Public License v3
Requires-Python: >=3.6
Requires-Dist: odoo14-addon-ssi-accounting-entry-mixin
Requires-Dist: odoo14-addon-ssi-company-currency-mixin
Requires-Dist: odoo14-addon-ssi-master-data-mixin
Requires-Dist: odoo14-addon-ssi-stock-fixed-asset
Requires-Dist: odoo14-addon-ssi-transaction-cancel-mixin
Requires-Dist: odoo14-addon-ssi-transaction-confirm-mixin
Requires-Dist: odoo14-addon-ssi-transaction-done-mixin
Requires-Dist: odoo<14.1dev,>=14.0a
